geodistpy/__init__.py
geodistpy/distance.py
geodistpy/geodesic.py
geodistpy-0.1.3.dist-info/LICENSE
geodistpy-0.1.3.dist-info/METADATA
geodistpy-0.1.3.dist-info/WHEEL
geodistpy-0.1.3.dist-info/RECORD
