Metadata-Version: 2.1
Name: geodistpy
Version: 0.1.3
Summary: For fast geodesic calculations
License: MIT
Keywords: geodesic,harvesine
Author: Pawan
Author-email: pawanjain.432@gmail.com
Requires-Python: >=3.9,<3.13
Classifier: Development Status :: 4 - Beta
Classifier: License :: OSI Approved :: MIT License
Classifier: Natural Language :: English
Classifier: Programming Language :: Python :: 3
Classifier: Programming Language :: Python :: 3.9
Classifier: Programming Language :: Python :: 3.10
Classifier: Programming Language :: Python :: 3.11
Classifier: Programming Language :: Python :: 3.12
Classifier: Topic :: Scientific/Engineering :: GIS
Requires-Dist: geographiclib (>=2.0,<3.0)
Requires-Dist: numba (>=0.60.0,<0.61.0)
Requires-Dist: numpy (>=1.26.4,<2.0.0)
Requires-Dist: scipy (>=1.13.1,<2.0.0) ; python_version >= "3.9" and python_version < "4.0"
Requires-Dist: scipy (>=1.14.1,<2.0.0) ; python_version >= "3.10" and python_version < "3.13"
